RedWebhook/__init__.py
RedWebhook/__main__.py
RedWebhook/exceptions.py
RedWebhook/webhook.py
tests/__init__.py
tests/test_redwebhook.py
RedWebhook-0.1.0.dist-info/LICENSE
RedWebhook-0.1.0.dist-info/METADATA
RedWebhook-0.1.0.dist-info/WHEEL
RedWebhook-0.1.0.dist-info/entry_points.txt
RedWebhook-0.1.0.dist-info/top_level.txt
RedWebhook-0.1.0.dist-info/RECORD
